pyfume/BuildTakagiSugeno.py
pyfume/Clustering.py
pyfume/EstimateAntecendentSet.py
pyfume/EstimateConsequentParameters.py
pyfume/FeatureSelection.py
pyfume/FireStrengthCalculator.py
pyfume/LoadData.py
pyfume/Sampler.py
pyfume/SimpfulModelBuilder.py
pyfume/Splitter.py
pyfume/Tester.py
pyfume/__init__.py
pyfume/pyfume.py
pyfume/simpfulfier.py
pyFUME-0.3.4.dist-info/LICENSE
pyFUME-0.3.4.dist-info/METADATA
pyFUME-0.3.4.dist-info/WHEEL
pyFUME-0.3.4.dist-info/top_level.txt
pyFUME-0.3.4.dist-info/RECORD
