Metadata-Version: 2.1
Name: pyFUME
Version: 0.3.4
Summary: A Python package for fuzzy model estimation
Home-page: https://github.com/CaroFuchs/pyFUME
Author: Caro Fuchs
Author-email: c.e.m.fuchs@tue.nl
License: LICENSE.txt
Keywords: fuzzy logic,fuzzy inference systems,fuzzy model,data-driven,model estimation,machine learning
Classifier: Programming Language :: Python :: 3
Classifier: License :: OSI Approved :: GNU General Public License (GPL)
Classifier: Operating System :: OS Independent
Requires-Python: >=3.8
License-File: LICENSE
Requires-Dist: scipy==1.10.1
Requires-Dist: numpy==1.24.4
Requires-Dist: simpful==2.12.0
Requires-Dist: fst-pso==1.8.1
Requires-Dist: pandas==1.5.3
